integrity/__init__.py
integrity/api.py
integrity/components.py
integrity/hooks.py
integrity/plugin.py
integrity-0.9.0.dist-info/LICENSE
integrity-0.9.0.dist-info/WHEEL
integrity-0.9.0.dist-info/METADATA
integrity-0.9.0.dist-info/RECORD
