Metadata-Version: 2.1
Name: integrity
Version: 0.9.0
Summary: Development facilities for the bolt environment
Home-page: https://github.com/thewii/integrity
License: MIT
Keywords: beet,minecraft,bolt,mecha
Author: TheWii
Requires-Python: >=3.10,<4.0
Classifier: License :: OSI Approved :: MIT License
Classifier: Programming Language :: Python :: 3
Classifier: Programming Language :: Python :: 3.10
Requires-Dist: beet (>=0.63.1)
Requires-Dist: bolt (>=0.16)
Requires-Dist: mecha (>=0.48.1)
Project-URL: Repository, https://github.com/thewii/integrity
